dmitri_latex/latex_lib/__init__.py
dmitri_latex/latex_lib/funcs.py
dmitritsiu_latex_lib-0.1.4.dist-info/METADATA
dmitritsiu_latex_lib-0.1.4.dist-info/WHEEL
dmitritsiu_latex_lib-0.1.4.dist-info/RECORD
