Metadata-Version: 2.4
Name: dmitritsiu-latex-lib
Version: 0.1.4
Summary: This is a LaTeX library created for MHS Python HW
Author: Dmitri Tsiu
Author-email: laoqiu1015@gmail.com
Requires-Python: >=3.11
Classifier: Programming Language :: Python :: 3
Classifier: Programming Language :: Python :: 3.11
Classifier: Programming Language :: Python :: 3.12
Classifier: Programming Language :: Python :: 3.13
Classifier: Programming Language :: Python :: 3.14
